rware/__init__.py
rware/rendering.py
rware/warehouse.py
rware/utils/__init__.py
rware/utils/spaces.py
rware/utils/wrappers.py
rware-2.0.0.dist-info/LICENSE
rware-2.0.0.dist-info/METADATA
rware-2.0.0.dist-info/WHEEL
rware-2.0.0.dist-info/top_level.txt
rware-2.0.0.dist-info/RECORD
