Metadata-Version: 2.1
Name: rware
Version: 2.0.0
Summary: Multi-Robot Warehouse environment for reinforcement learning
Home-page: https://github.com/semitable/robotic-warehouse
Author: Filippos Christianos
Classifier: Intended Audience :: Developers
Classifier: Programming Language :: Python :: 3.7
License-File: LICENSE
Requires-Dist: numpy
Requires-Dist: gymnasium
Requires-Dist: pyglet<2
Requires-Dist: networkx
Provides-Extra: test
Requires-Dist: pytest; extra == "test"
